Metadata-Version: 1.0
Name: clvnshi-distributions
Version: 0.1
Summary: Gaussian and Binomial distributions
Home-page: UNKNOWN
Author: Calvin Shi
Author-email: clvnshi@outlook.com
License: UNKNOWN
Platform: UNKNOWN
